yelpfusion3/__init__.py
yelpfusion3/client.py
yelpfusion3/endpoint.py
yelpfusion3/model.py
yelpfusion3/settings.py
yelpfusion3/business/__init__.py
yelpfusion3/business/endpoint.py
yelpfusion3/business/model.py
yelpfusion3/category/__init__.py
yelpfusion3/category/endpoint.py
yelpfusion3/category/model.py
yelpfusion3/event/__init__.py
yelpfusion3/event/endpoint.py
yelpfusion3/event/model.py
yelpfusion3-1.0.4.dist-info/METADATA
yelpfusion3-1.0.4.dist-info/WHEEL
yelpfusion3-1.0.4.dist-info/licenses/LICENSE
yelpfusion3-1.0.4.dist-info/RECORD
