Metadata-Version: 2.1
Name: yelpfusion3
Version: 1.0.4
Project-URL: Documentation, https://yelpfusion3.readthedocs.io/en/latest/index.html
Project-URL: Issues, https://github.com/benonsocial/yelpfusion3/issues
Project-URL: Source, https://github.com/benonsocial/yelpfusion3
Author: Ben Tran
License-File: LICENSE
Keywords: api,fusion,yelp
Classifier: Intended Audience :: Developers
Classifier: License :: OSI Approved :: MIT License
Classifier: Operating System :: OS Independent
Classifier: Programming Language :: Python :: 3
Classifier: Programming Language :: Python :: 3.9
Classifier: Programming Language :: Python :: 3.10
Classifier: Topic :: Internet
Classifier: Topic :: Software Development
Classifier: Topic :: Software Development :: Libraries
Classifier: Topic :: Software Development :: Libraries :: Application Frameworks
Classifier: Topic :: Software Development :: Libraries :: Python Modules
Requires-Python: >=3.9
Requires-Dist: pycountry
Requires-Dist: pydantic
Requires-Dist: requests
Requires-Dist: validators
